<?xml version="1.0"?>
<opencv_storage>
<stage8>
  <maxWeakCount>3</maxWeakCount>
  <stageThreshold>-1.4539685249328613e+00</stageThreshold>
  <weakClassifiers>
    <_>
      <internalNodes>
        0 -1 89416 -1.0864110291004181e-01</internalNodes>
      <leafValues>
        3.6000001430511475e-01 -9.2167830467224121e-01</leafValues></_>
    <_>
      <internalNodes>
        0 -1 104751 4.9297739751636982e-03</internalNodes>
      <leafValues>
        -7.5980359315872192e-01 5.3365170955657959e-01</leafValues></_>
    <_>
      <internalNodes>
        0 -1 73650 4.9621932208538055e-02</internalNodes>
      <leafValues>
        -9.9113470315933228e-01 2.2751344740390778e-01</leafValues></_></weakClassifiers></stage8>
</opencv_storage>
